odoo/addons/pos_order_return_traceability/README.rst
odoo/addons/pos_order_return_traceability/__init__.py
odoo/addons/pos_order_return_traceability/__manifest__.py
odoo/addons/pos_order_return_traceability/i18n/es.po
odoo/addons/pos_order_return_traceability/i18n/it.po
odoo/addons/pos_order_return_traceability/i18n/pos_order_return_traceability.pot
odoo/addons/pos_order_return_traceability/models/__init__.py
odoo/addons/pos_order_return_traceability/models/pos_order.py
odoo/addons/pos_order_return_traceability/readme/CONTRIBUTORS.rst
odoo/addons/pos_order_return_traceability/readme/DESCRIPTION.rst
odoo/addons/pos_order_return_traceability/readme/ROADMAP.rst
odoo/addons/pos_order_return_traceability/static/description/icon.png
odoo/addons/pos_order_return_traceability/static/description/index.html
odoo/addons/pos_order_return_traceability/static/src/js/models.js
odoo/addons/pos_order_return_traceability/static/src/js/widgets.js
odoo/addons/pos_order_return_traceability/static/src/xml/pos.xml
odoo/addons/pos_order_return_traceability/tests/__init__.py
odoo/addons/pos_order_return_traceability/tests/test_module.py
odoo/addons/pos_order_return_traceability/views/pos_templates.xml
odoo12_addon_pos_order_return_traceability-12.0.1.0.1.dist-info/METADATA
odoo12_addon_pos_order_return_traceability-12.0.1.0.1.dist-info/WHEEL
odoo12_addon_pos_order_return_traceability-12.0.1.0.1.dist-info/top_level.txt
odoo12_addon_pos_order_return_traceability-12.0.1.0.1.dist-info/RECORD
