Metadata-Version: 2.1
Name: odoo12-addon-pos-order-return-traceability
Version: 12.0.1.0.1
Summary: Adds full return traceability to POS frontend
Home-page: https://github.com/OCA/pos
Author: Odoo Community Association (OCA), Solvos
Author-email: support@odoo-community.org
License: AGPL-3
Platform: UNKNOWN
Classifier: Programming Language :: Python
Classifier: Framework :: Odoo
Classifier: Framework :: Odoo :: 12.0
Classifier: License :: OSI Approved :: GNU Affero General Public License v3
Requires-Python: >=3.5
Requires-Dist: odoo12-addon-pos-order-mgmt
Requires-Dist: odoo12-addon-pos-order-return
Requires-Dist: odoo (<12.1dev,>=12.0a)
